imessage/__init__.py
py_imessage_shortcuts-1.0.2.dist-info/LICENSE
py_imessage_shortcuts-1.0.2.dist-info/METADATA
py_imessage_shortcuts-1.0.2.dist-info/WHEEL
py_imessage_shortcuts-1.0.2.dist-info/top_level.txt
py_imessage_shortcuts-1.0.2.dist-info/RECORD
