Metadata-Version: 2.1
Name: py-imessage-shortcuts
Version: 1.0.2
Summary: Send iMessages using Python through the Shortcuts app.
Home-page: https://github.com/kevinschaich/py-imessage-shortcuts
Author: Kevin Schaich
Author-email: schaich.kevin@gmail.com
License: UNKNOWN
Project-URL: Bug Tracker, https://github.com/kevinschaich/py-imessage-shortcuts/issues
Platform: UNKNOWN
Classifier: Programming Language :: Python :: 3
Classifier: License :: OSI Approved :: MIT License
Classifier: Operating System :: OS Independent
Requires-Python: >=3.6
License-File: LICENSE
